pymeos/__init__.py
pymeos/db.py
pymeos/factory.py
pymeos/boxes/__init__.py
pymeos/boxes/stbox.py
pymeos/boxes/tbox.py
pymeos/examples/__init__.py
pymeos/examples/box.py
pymeos/examples/box_asyncpg.py
pymeos/examples/box_psycopg.py
pymeos/examples/db_connect.py
pymeos/examples/tbool.py
pymeos/examples/tbool_asyncpg.py
pymeos/examples/tbool_psycopg.py
pymeos/examples/tfloat.py
pymeos/examples/tfloat_asyncpg.py
pymeos/examples/tfloat_psycopg.py
pymeos/examples/tgeogpoint.py
pymeos/examples/tgeogpoint_asyncpg.py
pymeos/examples/tgeogpoint_psycopg.py
pymeos/examples/tgeompoint.py
pymeos/examples/tgeompoint_asyncpg.py
pymeos/examples/tgeompoint_psycopg.py
pymeos/examples/time.py
pymeos/examples/time_asyncpg.py
pymeos/examples/time_psycopg.py
pymeos/examples/tint.py
pymeos/examples/tint_asyncpg.py
pymeos/examples/tint_psycopg.py
pymeos/examples/ttext.py
pymeos/examples/ttext_asyncpg.py
pymeos/examples/ttext_psycopg.py
pymeos/main/__init__.py
pymeos/main/tbool.py
pymeos/main/tfloat.py
pymeos/main/tint.py
pymeos/main/tnumber.py
pymeos/main/tpoint.py
pymeos/main/ttext.py
pymeos/temporal/__init__.py
pymeos/temporal/temporal.py
pymeos/temporal/tinstant.py
pymeos/temporal/tinstantset.py
pymeos/temporal/tsequence.py
pymeos/temporal/tsequenceset.py
pymeos/time/__init__.py
pymeos/time/period.py
pymeos/time/periodset.py
pymeos/time/timestamp.py
pymeos/time/timestampset.py
pymeos_temp-0.0.5.dist-info/LICENSE
pymeos_temp-0.0.5.dist-info/METADATA
pymeos_temp-0.0.5.dist-info/WHEEL
pymeos_temp-0.0.5.dist-info/top_level.txt
pymeos_temp-0.0.5.dist-info/RECORD
