Metadata-Version: 2.1
Name: pymeos-temp
Version: 0.0.5
Summary: PyMEOS wrapper for the MEOS C Library.
Author-email: Víctor Diví <vdiviloper@gmail.com>
License: -------------------------------------------------------------------------------
Project-URL: Homepage, https://github.com/MobilityDB/PyMEOS
Project-URL: Bug Tracker, https://github.com/MobilityDB/PyMEOS/issues
Classifier: Programming Language :: Python :: 3
Classifier: License :: OSI Approved :: MIT License
Classifier: Operating System :: OS Independent
Requires-Python: >=3.7
License-File: LICENSE
Requires-Dist: pymeos-cffi
Requires-Dist: python-dateutil
Requires-Dist: spans
Requires-Dist: postgis
Requires-Dist: shapely
Requires-Dist: geopandas
